{
  "id": "rss-20260605-011",
  "title": "LeanMarathon: Toward Reliable AI Co-Mathematicians through Long-Horizon Lean Autoformalization",
  "source": "rss:arXiv cs.AI",
  "source_url": "https://arxiv.org/abs/2606.05400",
  "author": "arXiv cs.AI",
  "published_at": "2026-06-05T09:21:58.422414+00:00",
  "collected_at": "2026-06-05T09:21:58.422414+00:00",
  "summary": "该论文提出了LeanMarathon，一种通过长程自动形式化方法提升AI数学协作者可靠性的技术。核心价值在于利用Lean证明助手进行长序列推理，增强AI在数学证明中的准确性和鲁棒性。",
  "score": 7,
  "tags": [
    "reasoning",
    "code-generation"
  ],
  "audience": "intermediate",
  "status": "review",
  "updated_at": "2026-06-05T09:23:21.685943+00:00"
}