{
  "id": "rss-20260528-014",
  "title": "Discovery Agents for Real-Time Analytics: Toward Proactive Insight Systems",
  "source": "rss:arXiv cs.AI",
  "source_url": "https://arxiv.org/abs/2605.27571",
  "author": "arXiv cs.AI",
  "published_at": "2026-05-28T09:29:24.796649+00:00",
  "collected_at": "2026-05-28T09:29:24.796649+00:00",
  "summary": "本文提出了一种名为“Discovery Agents”的新型AI系统，旨在实现实时分析中的主动洞察。通过将智能代理与实时数据流结合，系统能够自动检测模式、异常和趋势，从而在用户查询之前提供有价值的分析结果，显著提升决策效率。",
  "score": 7,
  "tags": [
    "agent",
    "tool-use",
    "reasoning"
  ],
  "audience": "intermediate",
  "status": "review",
  "updated_at": "2026-05-28T09:31:00.602717+00:00"
}