{
  "id": "rss-20260613-004",
  "title": "How an Agent Built a 3D Paris Gallery by Chaining Two Hugging Face Spaces",
  "source": "rss:Hugging Face Blog",
  "source_url": "https://huggingface.co/blog/mishig/spaces-agents-md",
  "author": "Hugging Face Blog",
  "published_at": "2026-06-13T09:14:26.014260+00:00",
  "collected_at": "2026-06-13T09:14:26.014260+00:00",
  "summary": "该内容展示了如何通过链式调用两个 Hugging Face Spaces 构建一个 3D 巴黎画廊，体现了 AI Agent 在工具编排和空间生成方面的能力。其核心价值在于演示了多步骤任务中 Agent 的自主执行与模型协作，为创意应用提供了可复用的技术思路。",
  "score": 7,
  "tags": [
    "agent",
    "tool-use",
    "vision"
  ],
  "audience": "intermediate",
  "status": "review",
  "updated_at": "2026-06-13T09:15:42.437319+00:00"
}