{
  "id": "rss-20260704-004",
  "title": "ScarfBench: Benchmarking AI Agents for Enterprise Java Framework Migration",
  "source": "rss:Hugging Face Blog",
  "source_url": "https://huggingface.co/blog/ibm-research/scarfbench",
  "author": "Hugging Face Blog",
  "published_at": "2026-07-04T10:20:10.357402+00:00",
  "collected_at": "2026-07-04T10:20:10.357402+00:00",
  "summary": "ScarfBench 是一个用于评估 AI 代理在企业级 Java 框架迁移任务中性能的基准测试。它旨在衡量 AI 代理在复杂、真实的软件工程场景中的能力，特别是处理大型代码库和框架迁移的挑战。该基准测试为评估和比较不同 AI 代理在特定企业级任务上的表现提供了标准化方法。",
  "score": 7,
  "tags": [
    "agent",
    "evaluation",
    "code-generation"
  ],
  "audience": "advanced",
  "status": "review",
  "updated_at": "2026-07-04T10:21:27.614861+00:00"
}