{
  "id": "rss-20260626-013",
  "title": "Governing Actions, Not Agents: Institutional Attestation as a Governance Model for Autonomous AI Systems",
  "source": "rss:arXiv cs.AI",
  "source_url": "https://arxiv.org/abs/2606.26298",
  "author": "arXiv cs.AI",
  "published_at": "2026-06-26T09:17:50.940705+00:00",
  "collected_at": "2026-06-26T09:17:50.940705+00:00",
  "summary": "该论文提出了一种基于机构认证的治理模型，用于管理自主AI系统的行为，而非直接控制智能体本身。核心价值在于通过制度化的认证机制来确保AI系统的安全性和合规性，为AI治理提供了新的思路。",
  "score": 7,
  "tags": [
    "agent",
    "security"
  ],
  "audience": "intermediate",
  "status": "review",
  "updated_at": "2026-06-26T09:19:10.799603+00:00"
}