{
  "id": "rss-20260529-012",
  "title": "Orthogonal Concept Erasure for Diffusion Models",
  "source": "rss:arXiv cs.AI",
  "source_url": "https://arxiv.org/abs/2605.28902",
  "author": "arXiv cs.AI",
  "published_at": "2026-05-29T09:24:08.365920+00:00",
  "collected_at": "2026-05-29T09:24:08.365920+00:00",
  "summary": "该论文提出了一种正交概念擦除方法，用于从扩散模型中移除特定概念，同时保持模型生成其他内容的能力。该方法通过正交投影技术实现精确的概念移除，具有较高的实用价值。",
  "score": 7,
  "tags": [
    "vision",
    "fine-tuning"
  ],
  "audience": "intermediate",
  "status": "review",
  "updated_at": "2026-05-29T09:25:12.530423+00:00"
}